LICENSE.txt
MANIFEST.in
README.rst
pylintrc
pyproject.toml
tox.ini
data/A_Lovers_Complaint.pdf
data/pages.zip
data/pages/A_Lovers_Complaint_1.pdf
data/pages/A_Lovers_Complaint_2.pdf
data/pages/A_Lovers_Complaint_3.pdf
data/pages/A_Lovers_Complaint_4.pdf
data/pages/A_Lovers_Complaint_5.pdf
data/pages/A_Lovers_Complaint_6.pdf
src/imagedata_format_pdf/__init__.py
src/imagedata_format_pdf/pdfplugin.py
src/imagedata_format_pdf.egg-info/PKG-INFO
src/imagedata_format_pdf.egg-info/SOURCES.txt
src/imagedata_format_pdf.egg-info/dependency_links.txt
src/imagedata_format_pdf.egg-info/requires.txt
src/imagedata_format_pdf.egg-info/top_level.txt
tests/__init__.py
tests/context.py
tests/test_formats_pdf.py