Metadata-Version: 2.4
Name: imagedata_format_pdf
Version: 0.0.2
Summary: Imagedata format plugin for reading PDF files as encapsulated PDF
Author-email: Erling Andersen <Erling.Andersen@Helse-Bergen.NO>
Maintainer-email: Erling Andersen <Erling.Andersen@Helse-Bergen.NO>
License: MIT License
Project-URL: Documentation, https://imagedata.readthedocs.io
Project-URL: SourceCode, https://github.com/erling6232/imagedata_format_pdf
Keywords: dicom,python,medical,imaging,pdf
Classifier: Programming Language :: Python :: 3
Classifier: Development Status :: 4 - Beta
Classifier: Environment :: Other Environment
Classifier: Intended Audience :: Developers
Classifier: Intended Audience :: Healthcare Industry
Classifier: Intended Audience :: Science/Research
Classifier: License :: OSI Approved :: MIT License
Classifier: Operating System :: OS Independent
Classifier: Topic :: Software Development :: Libraries :: Python Modules
Classifier: Topic :: Scientific/Engineering :: Medical Science Apps.
Requires-Python: <3.14,>=3.9
License-File: LICENSE.txt
Requires-Dist: setuptools
Requires-Dist: imagedata<4,>=3.8.13
Requires-Dist: pypdfium2
Dynamic: license-file
